monday_item_parser/__init__.py
monday_item_parser/exceptions.py
monday_item_parser/fields/__init__.py
monday_item_parser/fields/checkbox.py
monday_item_parser/fields/country.py
monday_item_parser/fields/date.py
monday_item_parser/fields/dropdown.py
monday_item_parser/fields/email.py
monday_item_parser/fields/field.py
monday_item_parser/fields/helpers.py
monday_item_parser/fields/link.py
monday_item_parser/fields/location.py
monday_item_parser/fields/mirror.py
monday_item_parser/fields/number.py
monday_item_parser/fields/people.py
monday_item_parser/fields/phone.py
monday_item_parser/fields/status.py
monday_item_parser/fields/tags.py
monday_item_parser/fields/text.py
monday_item_parser/fields/timeline.py
monday_item_parser/helpers.py
monday_item_parser/item.py
monday_item_parser-0.2.15.dist-info/LICENSE
monday_item_parser-0.2.15.dist-info/METADATA
monday_item_parser-0.2.15.dist-info/WHEEL
monday_item_parser-0.2.15.dist-info/RECORD
