Metadata-Version: 2.1
Name: monday-item-parser
Version: 0.2.15
Summary: monday-item-parser is a library used to define Monday items structure in a specific board, and lets the user fetch, create, update and delete items from this board.
Author: Aviv Atedgi
Author-email: aviv.atedgi2000@gmail.com
Requires-Python: >=3.9,<3.13
Classifier: Programming Language :: Python :: 3
Classifier: Programming Language :: Python :: 3.9
Classifier: Programming Language :: Python :: 3.10
Classifier: Programming Language :: Python :: 3.11
Requires-Dist: bidict (>=0.21.4,<0.22.0)
Requires-Dist: dataclasses-json (>=0.5.14,<0.6.0)
Requires-Dist: monday (>=1.2.7,<2.0.0)
Requires-Dist: requests (>=2.27.1,<3.0.0)
